plone.rfc822-3.0.2-py3.13-nspkg.pth
plone/rfc822/__init__.py
plone/rfc822/_utils.py
plone/rfc822/configure.zcml
plone/rfc822/defaultfields.py
plone/rfc822/fields.rst
plone/rfc822/interfaces.py
plone/rfc822/message.rst
plone/rfc822/supermodel.py
plone/rfc822/supermodel.rst
plone/rfc822/tests.py
plone_rfc822-3.0.2.dist-info/METADATA
plone_rfc822-3.0.2.dist-info/WHEEL
plone_rfc822-3.0.2.dist-info/namespace_packages.txt
plone_rfc822-3.0.2.dist-info/top_level.txt
plone_rfc822-3.0.2.dist-info/RECORD
