Metadata-Version: 2.4
Name: plone.rfc822
Version: 3.0.2
Summary: RFC822 marshalling for zope.schema fields
Home-page: https://pypi.org/project/plone.rfc822
Author: Martin Aspeli and contributors
Author-email: optilude@gmail.com
License: BSD
Keywords: zope schema rfc822
Classifier: Development Status :: 5 - Production/Stable
Classifier: Framework :: Plone
Classifier: Framework :: Plone :: 6.0
Classifier: Framework :: Plone :: Core
Classifier: Programming Language :: Python
Classifier: Programming Language :: Python :: 3.8
Classifier: Programming Language :: Python :: 3.9
Classifier: Programming Language :: Python :: 3.10
Classifier: Programming Language :: Python :: 3.11
Classifier: Topic :: Software Development :: Libraries :: Python Modules
Classifier: License :: OSI Approved :: BSD License
Requires-Python: >=3.8
Requires-Dist: python-dateutil
Requires-Dist: setuptools
Requires-Dist: zope.component
Requires-Dist: zope.interface
Requires-Dist: zope.schema
Provides-Extra: supermodel
Requires-Dist: plone.supermodel; extra == "supermodel"
Provides-Extra: test
Requires-Dist: plone.testing; extra == "test"
Requires-Dist: plone.supermodel; extra == "test"
Requires-Dist: zope.annotation; extra == "test"
Requires-Dist: zope.configuration; extra == "test"
Requires-Dist: persistent; extra == "test"
Dynamic: author
Dynamic: author-email
Dynamic: classifier
Dynamic: description
Dynamic: description-content-type
Dynamic: home-page
Dynamic: keywords
Dynamic: license
Dynamic: provides-extra
Dynamic: requires-dist
Dynamic: requires-python
Dynamic: summary
